{"GlobalPropertiesHash":"2ilJ2M8+ZdH0swl4cXFj9Ji8kay0R08ISE/fEc+OL0o=","FingerprintPatternsHash":"8ZRc1sGeVrPBx4lD717BgRaQekyh78QKV9SKsdt638U=","PropertyOverridesHash":"8ZRc1sGeVrPBx4lD717BgRaQekyh78QKV9SKsdt638U=","InputHashes":["jLEZfASWKHgp3pjqKsR0Y2GabDqRpyEZVHAnvL9HLds=","XcsV5wA9/sXWFjtsVAYTMOe\u002BOEaSBAnd/Py5dMRF\u002BuE=","webw4cPLhi4F22OVCHXnGKx8iSST5Qbqpk7YjtdKrts=","RYlqIRKD08/m0iRw8eefXBKPDVh61E0w7TBaTLcYVGs=","/pD4IZbuJTQsEPOy1saVJGf2djCoZy8qfuBIdoZXPA8=","UAz5XGo61UUKWXsOyaonBLoSRgUlcUTVzUYofRrF3z8=","hdEroKZiv1\u002B00sCj8XvNCKbgelWx8Dy2q27\u002B1QD9zVg=","O/tV9D9GRDdFQ/GlVuWboZ0y7c/KZuPtxPRrUNOJW6Y=","LK0jJxMRIbyvmGx2TFBr6w1luOt73NMdjUyPyL5p2sQ=","ee/6/KFgNW9SgXmUS/yd0Sk4uj/At1lgKvVet7MC8aA=","zFmCcUqfOXr4ya1g33CZi2H40XEK4d0BGyDLxy29NH4=","JO5MTeZo97\u002BQIwarPHyHmNI3xEDsyDYtrjXWKYHGl3Q=","qKv92eDtpJZ3vrwsy6ZdiB1Lx2uy5gByrvpmO4zB0qE=","iDlOhGYtk9blRNv6HXwxIThEh90OhmD4tugTiv8p\u002B/4=","VBLCW4cFTb9BaxqRbGuY9PRTzq89/g/NoCefZ\u002BZJW8s=","L\u002B7iOZz5RLlUNxPtOutUIF4IyVE8wUj9FyXBi/WJfso=","cZ7wDrjJm4jdKFJOQNZQ8/C2tVPALEduXA1vZoBl2ac=","B4jdc2KIK1aupfOZyvWCqR2XFfGH/D8RoPsw0r44TaE=","VUdA\u002BTECdgmCQGxrybboEB/vey854hwjwvFpBIVAvck=","AML1zNCipoLZdbb8uKJvu0Eb1SqGO0EZY4\u002BYhY2i7ds=","O/Zct/CQ9sfc7xtUPB2tubZZFkRUkpl68PJTMzPildA=","763uR6ho1jnfG5A6Z6X8eVGr8yJeb1DB5jY18rzSYxQ=","nX8BK9otqCwEh\u002BrHBYXxr5IiQn/cEmv5ftTSuE5eZLk=","8ycGqpx/OTCl/H8IgimNt8qf6/hkbU6tN8T7mCVWm0Y="],"CachedAssets":{"/pD4IZbuJTQsEPOy1saVJGf2djCoZy8qfuBIdoZXPA8=":{"Identity":"E:\\private\\structo\\structo\\Structo.API\\obj\\Debug\\net9.0\\compressed\\37cpa2ulfi-{0}-3zdagh37q2-3zdagh37q2.gz","SourceId":"Structo.API","SourceType":"Discovered","ContentRoot":"E:\\private\\structo\\structo\\Structo.API\\obj\\Debug\\net9.0\\compressed\\","BasePath":"/","RelativePath":"chunk-B3ZFPULb#[.{fingerprint=3zdagh37q2}]?.js.gz","AssetKind":"All","AssetMode":"All","AssetRole":"Alternative","AssetMergeBehavior":null,"AssetMergeSource":"","RelatedAsset":"E:\\private\\structo\\structo\\Structo.API\\wwwroot\\chunk-B3ZFPULb.js","AssetTraitName":"Content-Encoding","AssetTraitValue":"gzip","Fingerprint":"mja9pheayq","Integrity":"oppHf/t3J9lSS/26NpXWm0eWoo6sHcKFLYM7wdBshF0=","CopyToOutputDirectory":"Never","CopyToPublishDirectory":"PreserveNewest","OriginalItemSpec":"E:\\private\\structo\\structo\\Structo.API\\wwwroot\\chunk-B3ZFPULb.js","FileLength":6054,"LastWriteTime":"2026-07-13T21:12:37.6055264+00:00"},"jLEZfASWKHgp3pjqKsR0Y2GabDqRpyEZVHAnvL9HLds=":{"Identity":"E:\\private\\structo\\structo\\Structo.API\\obj\\Debug\\net9.0\\compressed\\zbng80a9b5-{0}-rhkn8ns7f7-rhkn8ns7f7.gz","SourceId":"Structo.API","SourceType":"Discovered","ContentRoot":"E:\\private\\structo\\structo\\Structo.API\\obj\\Debug\\net9.0\\compressed\\","BasePath":"/","RelativePath":"3rdpartylicenses#[.{fingerprint=rhkn8ns7f7}]?.txt.gz","AssetKind":"All","AssetMode":"All","AssetRole":"Alternative","AssetMergeBehavior":null,"AssetMergeSource":"","RelatedAsset":"E:\\private\\structo\\structo\\Structo.API\\wwwroot\\3rdpartylicenses.txt","AssetTraitName":"Content-Encoding","AssetTraitValue":"gzip","Fingerprint":"h10s9uj5t5","Integrity":"y79PvgAAcjD7ezf11yDinVuzObTo6dq1ZFXdzGr6qQ8=","CopyToOutputDirectory":"Never","CopyToPublishDirectory":"PreserveNewest","OriginalItemSpec":"E:\\private\\structo\\structo\\Structo.API\\wwwroot\\3rdpartylicenses.txt","FileLength":5486,"LastWriteTime":"2026-07-13T21:12:37.6245965+00:00"},"8ycGqpx/OTCl/H8IgimNt8qf6/hkbU6tN8T7mCVWm0Y=":{"Identity":"E:\\private\\structo\\structo\\Structo.API\\obj\\Debug\\net9.0\\compressed\\txyxx3mpwj-{0}-046or81o09-046or81o09.gz","SourceId":"Structo.API","SourceType":"Discovered","ContentRoot":"E:\\private\\structo\\structo\\Structo.API\\obj\\Debug\\net9.0\\compressed\\","BasePath":"/","RelativePath":"styles-UKTYNSTL#[.{fingerprint=046or81o09}]?.css.gz","AssetKind":"All","AssetMode":"All","AssetRole":"Alternative","AssetMergeBehavior":null,"AssetMergeSource":"","RelatedAsset":"E:\\private\\structo\\structo\\Structo.API\\wwwroot\\styles-UKTYNSTL.css","AssetTraitName":"Content-Encoding","AssetTraitValue":"gzip","Fingerprint":"zuceis89bj","Integrity":"mzphuA\u002BmnG4tImKqTH0GlcCql4B8zcmqNv/cvz3DW/A=","CopyToOutputDirectory":"Never","CopyToPublishDirectory":"PreserveNewest","OriginalItemSpec":"E:\\private\\structo\\structo\\Structo.API\\wwwroot\\styles-UKTYNSTL.css","FileLength":17438,"LastWriteTime":"2026-07-13T21:12:37.6245965+00:00"},"763uR6ho1jnfG5A6Z6X8eVGr8yJeb1DB5jY18rzSYxQ=":{"Identity":"E:\\private\\structo\\structo\\Structo.API\\obj\\Debug\\net9.0\\compressed\\g0tf47v7te-{0}-v11wi2yzm1-v11wi2yzm1.gz","SourceId":"Structo.API","SourceType":"Discovered","ContentRoot":"E:\\private\\structo\\structo\\Structo.API\\obj\\Debug\\net9.0\\compressed\\","BasePath":"/","RelativePath":"main-OU3TMB7V#[.{fingerprint=v11wi2yzm1}]?.js.gz","AssetKind":"All","AssetMode":"All","AssetRole":"Alternative","AssetMergeBehavior":null,"AssetMergeSource":"","RelatedAsset":"E:\\private\\structo\\structo\\Structo.API\\wwwroot\\main-OU3TMB7V.js","AssetTraitName":"Content-Encoding","AssetTraitValue":"gzip","Fingerprint":"yv05j8j1vq","Integrity":"Qun8zNOnDlD87jmL6ZCbTyeMasUUoC\u002BOpVnkcFlU9AY=","CopyToOutputDirectory":"Never","CopyToPublishDirectory":"PreserveNewest","OriginalItemSpec":"E:\\private\\structo\\structo\\Structo.API\\wwwroot\\main-OU3TMB7V.js","FileLength":118638,"LastWriteTime":"2026-07-13T21:12:37.6292717+00:00"},"VBLCW4cFTb9BaxqRbGuY9PRTzq89/g/NoCefZ\u002BZJW8s=":{"Identity":"E:\\private\\structo\\structo\\Structo.API\\obj\\Debug\\net9.0\\compressed\\f6g2ib8kmh-{0}-lx9xejr9f8-lx9xejr9f8.gz","SourceId":"Structo.API","SourceType":"Discovered","ContentRoot":"E:\\private\\structo\\structo\\Structo.API\\obj\\Debug\\net9.0\\compressed\\","BasePath":"/","RelativePath":"chunk-GQouxYE4#[.{fingerprint=lx9xejr9f8}]?.js.gz","AssetKind":"All","AssetMode":"All","AssetRole":"Alternative","AssetMergeBehavior":null,"AssetMergeSource":"","RelatedAsset":"E:\\private\\structo\\structo\\Structo.API\\wwwroot\\chunk-GQouxYE4.js","AssetTraitName":"Content-Encoding","AssetTraitValue":"gzip","Fingerprint":"l74fgnhybc","Integrity":"7\u002BCGuscnGV2wl3G0Mj94SUczuV3BBG5l1JGePHHB0lg=","CopyToOutputDirectory":"Never","CopyToPublishDirectory":"PreserveNewest","OriginalItemSpec":"E:\\private\\structo\\structo\\Structo.API\\wwwroot\\chunk-GQouxYE4.js","FileLength":1250,"LastWriteTime":"2026-07-13T21:12:37.619216+00:00"},"O/Zct/CQ9sfc7xtUPB2tubZZFkRUkpl68PJTMzPildA=":{"Identity":"E:\\private\\structo\\structo\\Structo.API\\obj\\Debug\\net9.0\\compressed\\lr2ic3h079-{0}-o3evxtd0c8-o3evxtd0c8.gz","SourceId":"Structo.API","SourceType":"Discovered","ContentRoot":"E:\\private\\structo\\structo\\Structo.API\\obj\\Debug\\net9.0\\compressed\\","BasePath":"/","RelativePath":"index#[.{fingerprint=o3evxtd0c8}]?.html.gz","AssetKind":"All","AssetMode":"All","AssetRole":"Alternative","AssetMergeBehavior":null,"AssetMergeSource":"","RelatedAsset":"E:\\private\\structo\\structo\\Structo.API\\wwwroot\\index.html","AssetTraitName":"Content-Encoding","AssetTraitValue":"gzip","Fingerprint":"u81xpnrqrh","Integrity":"ctZ6qbIfQs\u002BR61\u002BsQtoDbgVlR3OOY7noX69guw/yD0I=","CopyToOutputDirectory":"Never","CopyToPublishDirectory":"PreserveNewest","OriginalItemSpec":"E:\\private\\structo\\structo\\Structo.API\\wwwroot\\index.html","FileLength":3773,"LastWriteTime":"2026-07-13T21:12:37.6141864+00:00"},"O/tV9D9GRDdFQ/GlVuWboZ0y7c/KZuPtxPRrUNOJW6Y=":{"Identity":"E:\\private\\structo\\structo\\Structo.API\\obj\\Debug\\net9.0\\compressed\\g9i7g38jf9-{0}-2xtjf5w899-2xtjf5w899.gz","SourceId":"Structo.API","SourceType":"Discovered","ContentRoot":"E:\\private\\structo\\structo\\Structo.API\\obj\\Debug\\net9.0\\compressed\\","BasePath":"/","RelativePath":"chunk-C0hZCqax#[.{fingerprint=2xtjf5w899}]?.js.gz","AssetKind":"All","AssetMode":"All","AssetRole":"Alternative","AssetMergeBehavior":null,"AssetMergeSource":"","RelatedAsset":"E:\\private\\structo\\structo\\Structo.API\\wwwroot\\chunk-C0hZCqax.js","AssetTraitName":"Content-Encoding","AssetTraitValue":"gzip","Fingerprint":"o1uqevst2n","Integrity":"ZDt7W3VrbtvRGV6/pdchpG2wDdX0waRN4fuoMY\u002B2ZbI=","CopyToOutputDirectory":"Never","CopyToPublishDirectory":"PreserveNewest","OriginalItemSpec":"E:\\private\\structo\\structo\\Structo.API\\wwwroot\\chunk-C0hZCqax.js","FileLength":3654,"LastWriteTime":"2026-07-13T21:12:37.6225525+00:00"},"UAz5XGo61UUKWXsOyaonBLoSRgUlcUTVzUYofRrF3z8=":{"Identity":"E:\\private\\structo\\structo\\Structo.API\\obj\\Debug\\net9.0\\compressed\\w8hj8ilmrb-{0}-demnkux7tv-demnkux7tv.gz","SourceId":"Structo.API","SourceType":"Discovered","ContentRoot":"E:\\private\\structo\\structo\\Structo.API\\obj\\Debug\\net9.0\\compressed\\","BasePath":"/","RelativePath":"chunk-Bj-ZsQkx#[.{fingerprint=demnkux7tv}]?.js.gz","AssetKind":"All","AssetMode":"All","AssetRole":"Alternative","AssetMergeBehavior":null,"AssetMergeSource":"","RelatedAsset":"E:\\private\\structo\\structo\\Structo.API\\wwwroot\\chunk-Bj-ZsQkx.js","AssetTraitName":"Content-Encoding","AssetTraitValue":"gzip","Fingerprint":"ngi5rf1p78","Integrity":"t9PhBvNO6rAy6R\u002B/TojhdEOeWTralMEPboOa4a5Re5k=","CopyToOutputDirectory":"Never","CopyToPublishDirectory":"PreserveNewest","OriginalItemSpec":"E:\\private\\structo\\structo\\Structo.API\\wwwroot\\chunk-Bj-ZsQkx.js","FileLength":10762,"LastWriteTime":"2026-07-13T21:12:37.6245965+00:00"},"zFmCcUqfOXr4ya1g33CZi2H40XEK4d0BGyDLxy29NH4=":{"Identity":"E:\\private\\structo\\structo\\Structo.API\\obj\\Debug\\net9.0\\compressed\\bjsamfeqi5-{0}-08yimy4zou-08yimy4zou.gz","SourceId":"Structo.API","SourceType":"Discovered","ContentRoot":"E:\\private\\structo\\structo\\Structo.API\\obj\\Debug\\net9.0\\compressed\\","BasePath":"/","RelativePath":"chunk-D7JoaquQ#[.{fingerprint=08yimy4zou}]?.js.gz","AssetKind":"All","AssetMode":"All","AssetRole":"Alternative","AssetMergeBehavior":null,"AssetMergeSource":"","RelatedAsset":"E:\\private\\structo\\structo\\Structo.API\\wwwroot\\chunk-D7JoaquQ.js","AssetTraitName":"Content-Encoding","AssetTraitValue":"gzip","Fingerprint":"fqama6vu2c","Integrity":"KY6fa95oTzm21raodRGUuMIigKs81ef/NtBM\u002BSAD6cE=","CopyToOutputDirectory":"Never","CopyToPublishDirectory":"PreserveNewest","OriginalItemSpec":"E:\\private\\structo\\structo\\Structo.API\\wwwroot\\chunk-D7JoaquQ.js","FileLength":529,"LastWriteTime":"2026-07-13T21:12:37.5915575+00:00"},"VUdA\u002BTECdgmCQGxrybboEB/vey854hwjwvFpBIVAvck=":{"Identity":"E:\\private\\structo\\structo\\Structo.API\\obj\\Debug\\net9.0\\compressed\\5ggmupjyil-{0}-7b79zuffwl-7b79zuffwl.gz","SourceId":"Structo.API","SourceType":"Discovered","ContentRoot":"E:\\private\\structo\\structo\\Structo.API\\obj\\Debug\\net9.0\\compressed\\","BasePath":"/","RelativePath":"chunk-UQECVbA7#[.{fingerprint=7b79zuffwl}]?.js.gz","AssetKind":"All","AssetMode":"All","AssetRole":"Alternative","AssetMergeBehavior":null,"AssetMergeSource":"","RelatedAsset":"E:\\private\\structo\\structo\\Structo.API\\wwwroot\\chunk-UQECVbA7.js","AssetTraitName":"Content-Encoding","AssetTraitValue":"gzip","Fingerprint":"2s30l15klq","Integrity":"Ijyqie\u002BhyXUvYSUODP9CwfWSO5CQkxHdSA6CgYDIA90=","CopyToOutputDirectory":"Never","CopyToPublishDirectory":"PreserveNewest","OriginalItemSpec":"E:\\private\\structo\\structo\\Structo.API\\wwwroot\\chunk-UQECVbA7.js","FileLength":3572,"LastWriteTime":"2026-07-13T21:12:37.5915575+00:00"},"ee/6/KFgNW9SgXmUS/yd0Sk4uj/At1lgKvVet7MC8aA=":{"Identity":"E:\\private\\structo\\structo\\Structo.API\\obj\\Debug\\net9.0\\compressed\\ah8ynw52vi-{0}-6n79tfcjlr-6n79tfcjlr.gz","SourceId":"Structo.API","SourceType":"Discovered","ContentRoot":"E:\\private\\structo\\structo\\Structo.API\\obj\\Debug\\net9.0\\compressed\\","BasePath":"/","RelativePath":"chunk-D-VqIds-#[.{fingerprint=6n79tfcjlr}]?.js.gz","AssetKind":"All","AssetMode":"All","AssetRole":"Alternative","AssetMergeBehavior":null,"AssetMergeSource":"","RelatedAsset":"E:\\private\\structo\\structo\\Structo.API\\wwwroot\\chunk-D-VqIds-.js","AssetTraitName":"Content-Encoding","AssetTraitValue":"gzip","Fingerprint":"924mmd4t8s","Integrity":"EWjfPNL0/HVgBBZQoCsKfj1/A6J8ey0ZoyVqSLx7TZY=","CopyToOutputDirectory":"Never","CopyToPublishDirectory":"PreserveNewest","OriginalItemSpec":"E:\\private\\structo\\structo\\Structo.API\\wwwroot\\chunk-D-VqIds-.js","FileLength":1552,"LastWriteTime":"2026-07-13T21:12:37.5915575+00:00"},"LK0jJxMRIbyvmGx2TFBr6w1luOt73NMdjUyPyL5p2sQ=":{"Identity":"E:\\private\\structo\\structo\\Structo.API\\obj\\Debug\\net9.0\\compressed\\1l2q0aeqoe-{0}-ktgr38czd3-ktgr38czd3.gz","SourceId":"Structo.API","SourceType":"Discovered","ContentRoot":"E:\\private\\structo\\structo\\Structo.API\\obj\\Debug\\net9.0\\compressed\\","BasePath":"/","RelativePath":"chunk-CmWrst-t#[.{fingerprint=ktgr38czd3}]?.js.gz","AssetKind":"All","AssetMode":"All","AssetRole":"Alternative","AssetMergeBehavior":null,"AssetMergeSource":"","RelatedAsset":"E:\\private\\structo\\structo\\Structo.API\\wwwroot\\chunk-CmWrst-t.js","AssetTraitName":"Content-Encoding","AssetTraitValue":"gzip","Fingerprint":"rbwsx9aeqn","Integrity":"Wch5\u002BVSPbpHkEqtwG7kneM4kc/af5zUpwMy\u002BMgWfwGM=","CopyToOutputDirectory":"Never","CopyToPublishDirectory":"PreserveNewest","OriginalItemSpec":"E:\\private\\structo\\structo\\Structo.API\\wwwroot\\chunk-CmWrst-t.js","FileLength":12432,"LastWriteTime":"2026-07-13T21:12:37.6245965+00:00"},"JO5MTeZo97\u002BQIwarPHyHmNI3xEDsyDYtrjXWKYHGl3Q=":{"Identity":"E:\\private\\structo\\structo\\Structo.API\\obj\\Debug\\net9.0\\compressed\\nbfv2u469c-{0}-6mrll712ox-6mrll712ox.gz","SourceId":"Structo.API","SourceType":"Discovered","ContentRoot":"E:\\private\\structo\\structo\\Structo.API\\obj\\Debug\\net9.0\\compressed\\","BasePath":"/","RelativePath":"chunk-DChTjgoE#[.{fingerprint=6mrll712ox}]?.js.gz","AssetKind":"All","AssetMode":"All","AssetRole":"Alternative","AssetMergeBehavior":null,"AssetMergeSource":"","RelatedAsset":"E:\\private\\structo\\structo\\Structo.API\\wwwroot\\chunk-DChTjgoE.js","AssetTraitName":"Content-Encoding","AssetTraitValue":"gzip","Fingerprint":"zmqffjrcm6","Integrity":"m3\u002BlRsqS7/o624/fdgrhfKpIIzN2lxUPLGTdOsi9TrA=","CopyToOutputDirectory":"Never","CopyToPublishDirectory":"PreserveNewest","OriginalItemSpec":"E:\\private\\structo\\structo\\Structo.API\\wwwroot\\chunk-DChTjgoE.js","FileLength":6576,"LastWriteTime":"2026-07-13T21:12:37.6245965+00:00"},"iDlOhGYtk9blRNv6HXwxIThEh90OhmD4tugTiv8p\u002B/4=":{"Identity":"E:\\private\\structo\\structo\\Structo.API\\obj\\Debug\\net9.0\\compressed\\406ck8i81r-{0}-yqo6xsals7-yqo6xsals7.gz","SourceId":"Structo.API","SourceType":"Discovered","ContentRoot":"E:\\private\\structo\\structo\\Structo.API\\obj\\Debug\\net9.0\\compressed\\","BasePath":"/","RelativePath":"chunk-D_sgGNQw#[.{fingerprint=yqo6xsals7}]?.js.gz","AssetKind":"All","AssetMode":"All","AssetRole":"Alternative","AssetMergeBehavior":null,"AssetMergeSource":"","RelatedAsset":"E:\\private\\structo\\structo\\Structo.API\\wwwroot\\chunk-D_sgGNQw.js","AssetTraitName":"Content-Encoding","AssetTraitValue":"gzip","Fingerprint":"zceskibu5i","Integrity":"s4NiTJeNO91BE7XOm53NXPB/P5Inf\u002BUfb0cfG\u002ByhlRk=","CopyToOutputDirectory":"Never","CopyToPublishDirectory":"PreserveNewest","OriginalItemSpec":"E:\\private\\structo\\structo\\Structo.API\\wwwroot\\chunk-D_sgGNQw.js","FileLength":35012,"LastWriteTime":"2026-07-13T21:12:37.6251139+00:00"},"qKv92eDtpJZ3vrwsy6ZdiB1Lx2uy5gByrvpmO4zB0qE=":{"Identity":"E:\\private\\structo\\structo\\Structo.API\\obj\\Debug\\net9.0\\compressed\\5dosroc91z-{0}-erevi5meqt-erevi5meqt.gz","SourceId":"Structo.API","SourceType":"Discovered","ContentRoot":"E:\\private\\structo\\structo\\Structo.API\\obj\\Debug\\net9.0\\compressed\\","BasePath":"/","RelativePath":"chunk-DwCWa7U7#[.{fingerprint=erevi5meqt}]?.js.gz","AssetKind":"All","AssetMode":"All","AssetRole":"Alternative","AssetMergeBehavior":null,"AssetMergeSource":"","RelatedAsset":"E:\\private\\structo\\structo\\Structo.API\\wwwroot\\chunk-DwCWa7U7.js","AssetTraitName":"Content-Encoding","AssetTraitValue":"gzip","Fingerprint":"14lg4s0miq","Integrity":"Hz3QUFk37tvejtDnEM2e1kx\u002B\u002BGQD9NIeJCiocs1UDIE=","CopyToOutputDirectory":"Never","CopyToPublishDirectory":"PreserveNewest","OriginalItemSpec":"E:\\private\\structo\\structo\\Structo.API\\wwwroot\\chunk-DwCWa7U7.js","FileLength":43751,"LastWriteTime":"2026-07-13T21:12:37.6251139+00:00"},"L\u002B7iOZz5RLlUNxPtOutUIF4IyVE8wUj9FyXBi/WJfso=":{"Identity":"E:\\private\\structo\\structo\\Structo.API\\obj\\Debug\\net9.0\\compressed\\8rcw4w8ll4-{0}-mmosv1x1w3-mmosv1x1w3.gz","SourceId":"Structo.API","SourceType":"Discovered","ContentRoot":"E:\\private\\structo\\structo\\Structo.API\\obj\\Debug\\net9.0\\compressed\\","BasePath":"/","RelativePath":"chunk-grBodOAd#[.{fingerprint=mmosv1x1w3}]?.js.gz","AssetKind":"All","AssetMode":"All","AssetRole":"Alternative","AssetMergeBehavior":null,"AssetMergeSource":"","RelatedAsset":"E:\\private\\structo\\structo\\Structo.API\\wwwroot\\chunk-grBodOAd.js","AssetTraitName":"Content-Encoding","AssetTraitValue":"gzip","Fingerprint":"7xv7mojfdy","Integrity":"W8NRIxtKg6RwYenW5\u002BdmofuKzew9ttQCmtMY1Y3r5lQ=","CopyToOutputDirectory":"Never","CopyToPublishDirectory":"PreserveNewest","OriginalItemSpec":"E:\\private\\structo\\structo\\Structo.API\\wwwroot\\chunk-grBodOAd.js","FileLength":9161,"LastWriteTime":"2026-07-13T21:12:37.6245965+00:00"},"cZ7wDrjJm4jdKFJOQNZQ8/C2tVPALEduXA1vZoBl2ac=":{"Identity":"E:\\private\\structo\\structo\\Structo.API\\obj\\Debug\\net9.0\\compressed\\h7oinu8r5n-{0}-6bxu8dwmbs-6bxu8dwmbs.gz","SourceId":"Structo.API","SourceType":"Discovered","ContentRoot":"E:\\private\\structo\\structo\\Structo.API\\obj\\Debug\\net9.0\\compressed\\","BasePath":"/","RelativePath":"chunk-nxLDMh3P#[.{fingerprint=6bxu8dwmbs}]?.js.gz","AssetKind":"All","AssetMode":"All","AssetRole":"Alternative","AssetMergeBehavior":null,"AssetMergeSource":"","RelatedAsset":"E:\\private\\structo\\structo\\Structo.API\\wwwroot\\chunk-nxLDMh3P.js","AssetTraitName":"Content-Encoding","AssetTraitValue":"gzip","Fingerprint":"17d890cn4o","Integrity":"zR3NGukiqOJ1JMLaBklJmrSrn5YZeD5MyWo3Vw4qbRQ=","CopyToOutputDirectory":"Never","CopyToPublishDirectory":"PreserveNewest","OriginalItemSpec":"E:\\private\\structo\\structo\\Structo.API\\wwwroot\\chunk-nxLDMh3P.js","FileLength":337,"LastWriteTime":"2026-07-13T21:12:37.5915575+00:00"},"B4jdc2KIK1aupfOZyvWCqR2XFfGH/D8RoPsw0r44TaE=":{"Identity":"E:\\private\\structo\\structo\\Structo.API\\obj\\Debug\\net9.0\\compressed\\p2dw63fx8v-{0}-2fk3cmzwwd-2fk3cmzwwd.gz","SourceId":"Structo.API","SourceType":"Discovered","ContentRoot":"E:\\private\\structo\\structo\\Structo.API\\obj\\Debug\\net9.0\\compressed\\","BasePath":"/","RelativePath":"chunk-tobP6u7p#[.{fingerprint=2fk3cmzwwd}]?.js.gz","AssetKind":"All","AssetMode":"All","AssetRole":"Alternative","AssetMergeBehavior":null,"AssetMergeSource":"","RelatedAsset":"E:\\private\\structo\\structo\\Structo.API\\wwwroot\\chunk-tobP6u7p.js","AssetTraitName":"Content-Encoding","AssetTraitValue":"gzip","Fingerprint":"lf8bshpb62","Integrity":"jzBC9I9lD6nFWwLw2zIP1FMtIAaB/kYzIRswxdGo5Jc=","CopyToOutputDirectory":"Never","CopyToPublishDirectory":"PreserveNewest","OriginalItemSpec":"E:\\private\\structo\\structo\\Structo.API\\wwwroot\\chunk-tobP6u7p.js","FileLength":543,"LastWriteTime":"2026-07-13T21:12:37.5915575+00:00"},"hdEroKZiv1\u002B00sCj8XvNCKbgelWx8Dy2q27\u002B1QD9zVg=":{"Identity":"E:\\private\\structo\\structo\\Structo.API\\obj\\Debug\\net9.0\\compressed\\26u9sml209-{0}-kbz43ir9mz-kbz43ir9mz.gz","SourceId":"Structo.API","SourceType":"Discovered","ContentRoot":"E:\\private\\structo\\structo\\Structo.API\\obj\\Debug\\net9.0\\compressed\\","BasePath":"/","RelativePath":"chunk-BlQDn_Cl#[.{fingerprint=kbz43ir9mz}]?.js.gz","AssetKind":"All","AssetMode":"All","AssetRole":"Alternative","AssetMergeBehavior":null,"AssetMergeSource":"","RelatedAsset":"E:\\private\\structo\\structo\\Structo.API\\wwwroot\\chunk-BlQDn_Cl.js","AssetTraitName":"Content-Encoding","AssetTraitValue":"gzip","Fingerprint":"z7qx4mqxe2","Integrity":"/348RGpJXlgOHgN6iPQZf5k3XXTt3fatzDTWj8Djz04=","CopyToOutputDirectory":"Never","CopyToPublishDirectory":"PreserveNewest","OriginalItemSpec":"E:\\private\\structo\\structo\\Structo.API\\wwwroot\\chunk-BlQDn_Cl.js","FileLength":16946,"LastWriteTime":"2026-07-13T21:12:37.6245965+00:00"},"XcsV5wA9/sXWFjtsVAYTMOe\u002BOEaSBAnd/Py5dMRF\u002BuE=":{"Identity":"E:\\private\\structo\\structo\\Structo.API\\obj\\Debug\\net9.0\\compressed\\ythiqt0myh-{0}-m123gm9a0g-m123gm9a0g.gz","SourceId":"Structo.API","SourceType":"Discovered","ContentRoot":"E:\\private\\structo\\structo\\Structo.API\\obj\\Debug\\net9.0\\compressed\\","BasePath":"/","RelativePath":"assets/i18n/ar#[.{fingerprint=m123gm9a0g}]?.json.gz","AssetKind":"All","AssetMode":"All","AssetRole":"Alternative","AssetMergeBehavior":null,"AssetMergeSource":"","RelatedAsset":"E:\\private\\structo\\structo\\Structo.API\\wwwroot\\assets\\i18n\\ar.json","AssetTraitName":"Content-Encoding","AssetTraitValue":"gzip","Fingerprint":"eegns6hjz4","Integrity":"xvYPBVuFCMZi7gceAD\u002BeGwLg9NEYYqv1sTSCZBlmwWQ=","CopyToOutputDirectory":"Never","CopyToPublishDirectory":"PreserveNewest","OriginalItemSpec":"E:\\private\\structo\\structo\\Structo.API\\wwwroot\\assets\\i18n\\ar.json","FileLength":5673,"LastWriteTime":"2026-07-13T19:18:45.8294802+00:00"},"webw4cPLhi4F22OVCHXnGKx8iSST5Qbqpk7YjtdKrts=":{"Identity":"E:\\private\\structo\\structo\\Structo.API\\obj\\Debug\\net9.0\\compressed\\i13cck3lrj-{0}-zm47jbwdoj-zm47jbwdoj.gz","SourceId":"Structo.API","SourceType":"Discovered","ContentRoot":"E:\\private\\structo\\structo\\Structo.API\\obj\\Debug\\net9.0\\compressed\\","BasePath":"/","RelativePath":"assets/i18n/en#[.{fingerprint=zm47jbwdoj}]?.json.gz","AssetKind":"All","AssetMode":"All","AssetRole":"Alternative","AssetMergeBehavior":null,"AssetMergeSource":"","RelatedAsset":"E:\\private\\structo\\structo\\Structo.API\\wwwroot\\assets\\i18n\\en.json","AssetTraitName":"Content-Encoding","AssetTraitValue":"gzip","Fingerprint":"rgkz71b4tm","Integrity":"pfIUUSWmLuKbPiC5N/LRoEYRC\u002BuGcwMlRVOXQ9/EeVw=","CopyToOutputDirectory":"Never","CopyToPublishDirectory":"PreserveNewest","OriginalItemSpec":"E:\\private\\structo\\structo\\Structo.API\\wwwroot\\assets\\i18n\\en.json","FileLength":5135,"LastWriteTime":"2026-07-13T19:18:45.8145814+00:00"},"AML1zNCipoLZdbb8uKJvu0Eb1SqGO0EZY4\u002BYhY2i7ds=":{"Identity":"E:\\private\\structo\\structo\\Structo.API\\obj\\Debug\\net9.0\\compressed\\raobfy6ke9-{0}-vagikyz9qx-vagikyz9qx.gz","SourceId":"Structo.API","SourceType":"Discovered","ContentRoot":"E:\\private\\structo\\structo\\Structo.API\\obj\\Debug\\net9.0\\compressed\\","BasePath":"/","RelativePath":"favicon#[.{fingerprint=vagikyz9qx}]?.ico.gz","AssetKind":"All","AssetMode":"All","AssetRole":"Alternative","AssetMergeBehavior":null,"AssetMergeSource":"","RelatedAsset":"E:\\private\\structo\\structo\\Structo.API\\wwwroot\\favicon.ico","AssetTraitName":"Content-Encoding","AssetTraitValue":"gzip","Fingerprint":"spc2whqxhc","Integrity":"4JD5TBkaKkYJVw5DzZh1jKJdCSTQYxpre7fdXrSQ/P8=","CopyToOutputDirectory":"Never","CopyToPublishDirectory":"PreserveNewest","OriginalItemSpec":"E:\\private\\structo\\structo\\Structo.API\\wwwroot\\favicon.ico","FileLength":4212,"LastWriteTime":"2026-07-13T19:18:45.8294802+00:00"},"nX8BK9otqCwEh\u002BrHBYXxr5IiQn/cEmv5ftTSuE5eZLk=":{"Identity":"E:\\private\\structo\\structo\\Structo.API\\obj\\Debug\\net9.0\\compressed\\eopemj2fdf-{0}-fp1x7dnec5-fp1x7dnec5.gz","SourceId":"Structo.API","SourceType":"Discovered","ContentRoot":"E:\\private\\structo\\structo\\Structo.API\\obj\\Debug\\net9.0\\compressed\\","BasePath":"/","RelativePath":"OneSignalSDKWorker#[.{fingerprint=fp1x7dnec5}]?.js.gz","AssetKind":"All","AssetMode":"All","AssetRole":"Alternative","AssetMergeBehavior":null,"AssetMergeSource":"","RelatedAsset":"E:\\private\\structo\\structo\\Structo.API\\wwwroot\\OneSignalSDKWorker.js","AssetTraitName":"Content-Encoding","AssetTraitValue":"gzip","Fingerprint":"kcp8okpjcw","Integrity":"VGpV4DWiYPp8LdLc4NBxzV6NXg8V6CHSrDOXR72r9cU=","CopyToOutputDirectory":"Never","CopyToPublishDirectory":"PreserveNewest","OriginalItemSpec":"E:\\private\\structo\\structo\\Structo.API\\wwwroot\\OneSignalSDKWorker.js","FileLength":92,"LastWriteTime":"2026-07-13T19:18:45.8289754+00:00"},"RYlqIRKD08/m0iRw8eefXBKPDVh61E0w7TBaTLcYVGs=":{"Identity":"E:\\private\\structo\\structo\\Structo.API\\obj\\Debug\\net9.0\\compressed\\trkourzw2f-{0}-nlhv8n6am5-nlhv8n6am5.gz","SourceId":"Structo.API","SourceType":"Discovered","ContentRoot":"E:\\private\\structo\\structo\\Structo.API\\obj\\Debug\\net9.0\\compressed\\","BasePath":"/","RelativePath":"chunk-9kj1H1sq#[.{fingerprint=nlhv8n6am5}]?.js.gz","AssetKind":"All","AssetMode":"All","AssetRole":"Alternative","AssetMergeBehavior":null,"AssetMergeSource":"","RelatedAsset":"E:\\private\\structo\\structo\\Structo.API\\wwwroot\\chunk-9kj1H1sq.js","AssetTraitName":"Content-Encoding","AssetTraitValue":"gzip","Fingerprint":"yonx8ghzvj","Integrity":"zvFC\u002BiWIKPbXMb41sRhJoq5MewG6DrTAPcBJp8hT7eE=","CopyToOutputDirectory":"Never","CopyToPublishDirectory":"PreserveNewest","OriginalItemSpec":"E:\\private\\structo\\structo\\Structo.API\\wwwroot\\chunk-9kj1H1sq.js","FileLength":10058,"LastWriteTime":"2026-07-13T21:12:37.6245965+00:00"}},"CachedCopyCandidates":{}}