{"GlobalPropertiesHash":"/MlWZ4zAX6UuFpDsZavEk4nNLY8/AO0LmMgJ02c4I84=","FingerprintPatternsHash":"gq3WsqcKBUGTSNle7RKKyXRIwh7M8ccEqOqYvIzoM04=","PropertyOverridesHash":"8ZRc1sGeVrPBx4lD717BgRaQekyh78QKV9SKsdt638U=","InputHashes":["2\u002BNuyJGlzLGQIwf30i/VwLH6lxHUbHRhmz5lPoXw7/o=","VcFc75hEssvuHgbAyyMAonWUwx4rJS7RGv9jNv76JGU=","Nh9cyM7f4gTOUsXYky3iwx\u002BZgJRRAtKZNs0Xo6Quil8=","vTnqz\u002BxjeryvkeVkzmL9cgQtIjXyFaqPqDchX1uanGw=","ZgEPg7Jt26YY0Fd/YPTJwhlKfWpR3LCud0PttwqfYqo=","PHSmeVPpf2d5w\u002BGdMRwoi1H7moFsRfep1gjAwUgNnKY=","/bm7SGeStM6JxqcQoCjse94MsKxznheYFjUDmlSoiII=","ij\u002BC\u002BB77ZoU9LvrxrOtEaZn3wE1IhaRFBL4jWSYo3C0=","8ks3nQ5u1UI2DF7D0fU1fHUJDUK9jJDeqq49vLtozPk=","NKC/a3GCfq0HwhMOzEIyafLYCFVFg1US\u002BnhLTgkaZ0c=","d8dxIEQg7ZAF5LkmiKn7nH4QPTEYPO7Ac/eRcn2z6xU=","kmMqUrgMSskAHMMFQjZhvSTDrVI/n0QUrlnzrjhY/Ts=","TPoiUCcAXjsM1R7g6iSvD2b7QvShCn9f1uigYSzAQ8E=","JCfmUn9DQGohrkt0dkNHgnj2lj468IilPQMEaw3aJNM=","pmkISbvq6Sexst6ZtLQBN/TsOQ\u002B90VDWu1tLVmnSRY0=","XIBalfhpYpBtFN2qz1avnSFE6gyQaeWklROidTafXLs=","z4EtR\u002B67EIh9w1BBQ\u002BAKPkrC8J\u002BcXEA8bk4qbbZwtZs=","puYlqvbi18t8MKG3B76mHHNQN7PvibyuRXtrTeQ3hZI=","q9ATfcdqiJ1Wtrb/7IBukP6rZQNzNzpPUK/0Dea60os=","XyaPNxtqV9ri0f\u002B9tN964qhZz/QTWlPIifnsTBlPioM=","BXt3y80BFlCEF00RhXRKMxY2zfaTji4RZuoo6Gb\u002B6UI=","UhwYEn2Xs79C8luKQO8cp5msBS0e64fNp25lam4lCi8="],"CachedAssets":{"2\u002BNuyJGlzLGQIwf30i/VwLH6lxHUbHRhmz5lPoXw7/o=":{"Identity":"E:\\private\\structo\\structo\\Structo.API\\wwwroot\\3rdpartylicenses.txt","SourceId":"Structo.API","SourceType":"Discovered","ContentRoot":"E:\\private\\structo\\structo\\Structo.API\\wwwroot\\","BasePath":"_content/Structo.API","RelativePath":"3rdpartylicenses#[.{fingerprint}]?.txt","AssetKind":"All","AssetMode":"All","AssetRole":"Primary","AssetMergeBehavior":null,"AssetMergeSource":"","RelatedAsset":null,"AssetTraitName":null,"AssetTraitValue":null,"Fingerprint":"32truu82x3","Integrity":"JR6q\u002BkUudGePvR4z703BFBTUGFmR0YrqbP3RD9GlZq4=","CopyToOutputDirectory":"Never","CopyToPublishDirectory":"PreserveNewest","OriginalItemSpec":"wwwroot\\3rdpartylicenses.txt","FileLength":20782,"LastWriteTime":"2026-06-30T01:28:48.4844822+00:00"},"XyaPNxtqV9ri0f\u002B9tN964qhZz/QTWlPIifnsTBlPioM=":{"Identity":"E:\\private\\structo\\structo\\Structo.API\\wwwroot\\styles-57HBRLNK.css","SourceId":"Structo.API","SourceType":"Discovered","ContentRoot":"E:\\private\\structo\\structo\\Structo.API\\wwwroot\\","BasePath":"_content/Structo.API","RelativePath":"styles-57HBRLNK#[.{fingerprint}]?.css","AssetKind":"All","AssetMode":"All","AssetRole":"Primary","AssetMergeBehavior":null,"AssetMergeSource":"","RelatedAsset":null,"AssetTraitName":null,"AssetTraitValue":null,"Fingerprint":"l1sllps5jr","Integrity":"x0WgnwoZd3uUbehIvrjYLUrfaV6qnJwS31MqF6lR/ag=","CopyToOutputDirectory":"Never","CopyToPublishDirectory":"PreserveNewest","OriginalItemSpec":"wwwroot\\styles-57HBRLNK.css","FileLength":96461,"LastWriteTime":"2026-06-30T01:28:48.4767901+00:00"},"q9ATfcdqiJ1Wtrb/7IBukP6rZQNzNzpPUK/0Dea60os=":{"Identity":"E:\\private\\structo\\structo\\Structo.API\\wwwroot\\OneSignalSDKWorker.js","SourceId":"Structo.API","SourceType":"Discovered","ContentRoot":"E:\\private\\structo\\structo\\Structo.API\\wwwroot\\","BasePath":"_content/Structo.API","RelativePath":"OneSignalSDKWorker#[.{fingerprint}]?.js","AssetKind":"All","AssetMode":"All","AssetRole":"Primary","AssetMergeBehavior":null,"AssetMergeSource":"","RelatedAsset":null,"AssetTraitName":null,"AssetTraitValue":null,"Fingerprint":"fp1x7dnec5","Integrity":"Hc44Lw6x1Jy40gNuUWvOJtdHfgwFO71Ud/H27IsWOEc=","CopyToOutputDirectory":"Never","CopyToPublishDirectory":"PreserveNewest","OriginalItemSpec":"wwwroot\\OneSignalSDKWorker.js","FileLength":75,"LastWriteTime":"2023-04-14T22:59:41+00:00"},"puYlqvbi18t8MKG3B76mHHNQN7PvibyuRXtrTeQ3hZI=":{"Identity":"E:\\private\\structo\\structo\\Structo.API\\wwwroot\\main-QITJNSQ6.js","SourceId":"Structo.API","SourceType":"Discovered","ContentRoot":"E:\\private\\structo\\structo\\Structo.API\\wwwroot\\","BasePath":"_content/Structo.API","RelativePath":"main-QITJNSQ6#[.{fingerprint}]?.js","AssetKind":"All","AssetMode":"All","AssetRole":"Primary","AssetMergeBehavior":null,"AssetMergeSource":"","RelatedAsset":null,"AssetTraitName":null,"AssetTraitValue":null,"Fingerprint":"ih55x97w5h","Integrity":"BqCrB5qF/tJs\u002BUfGxSS1zYWQhpkLjDPsfoUwi7PukmY=","CopyToOutputDirectory":"Never","CopyToPublishDirectory":"PreserveNewest","OriginalItemSpec":"wwwroot\\main-QITJNSQ6.js","FileLength":392010,"LastWriteTime":"2026-06-30T01:28:48.4757891+00:00"},"z4EtR\u002B67EIh9w1BBQ\u002BAKPkrC8J\u002BcXEA8bk4qbbZwtZs=":{"Identity":"E:\\private\\structo\\structo\\Structo.API\\wwwroot\\index.html","SourceId":"Structo.API","SourceType":"Discovered","ContentRoot":"E:\\private\\structo\\structo\\Structo.API\\wwwroot\\","BasePath":"_content/Structo.API","RelativePath":"index#[.{fingerprint}]?.html","AssetKind":"All","AssetMode":"All","AssetRole":"Primary","AssetMergeBehavior":null,"AssetMergeSource":"","RelatedAsset":null,"AssetTraitName":null,"AssetTraitValue":null,"Fingerprint":"fwkysb4a0l","Integrity":"sfllppFoBgTkLqrOu1C5HoySVvnqSuSkwZ4oj/UjqOw=","CopyToOutputDirectory":"Never","CopyToPublishDirectory":"PreserveNewest","OriginalItemSpec":"wwwroot\\index.html","FileLength":23566,"LastWriteTime":"2026-06-30T01:28:48.4844822+00:00"},"XIBalfhpYpBtFN2qz1avnSFE6gyQaeWklROidTafXLs=":{"Identity":"E:\\private\\structo\\structo\\Structo.API\\wwwroot\\favicon.ico","SourceId":"Structo.API","SourceType":"Discovered","ContentRoot":"E:\\private\\structo\\structo\\Structo.API\\wwwroot\\","BasePath":"_content/Structo.API","RelativePath":"favicon#[.{fingerprint}]?.ico","AssetKind":"All","AssetMode":"All","AssetRole":"Primary","AssetMergeBehavior":null,"AssetMergeSource":"","RelatedAsset":null,"AssetTraitName":null,"AssetTraitValue":null,"Fingerprint":"vagikyz9qx","Integrity":"\u002BRAr6AKXwFKSB2B75Sd7T5C8qJ1lmI\u002BhdxuRx4lOgV8=","CopyToOutputDirectory":"Never","CopyToPublishDirectory":"PreserveNewest","OriginalItemSpec":"wwwroot\\favicon.ico","FileLength":15086,"LastWriteTime":"2026-06-23T09:03:05.164+00:00"},"pmkISbvq6Sexst6ZtLQBN/TsOQ\u002B90VDWu1tLVmnSRY0=":{"Identity":"E:\\private\\structo\\structo\\Structo.API\\wwwroot\\chunk-UJ7--WjT.js","SourceId":"Structo.API","SourceType":"Discovered","ContentRoot":"E:\\private\\structo\\structo\\Structo.API\\wwwroot\\","BasePath":"_content/Structo.API","RelativePath":"chunk-UJ7--WjT#[.{fingerprint}]?.js","AssetKind":"All","AssetMode":"All","AssetRole":"Primary","AssetMergeBehavior":null,"AssetMergeSource":"","RelatedAsset":null,"AssetTraitName":null,"AssetTraitValue":null,"Fingerprint":"6t9og3v7jo","Integrity":"Vgz7N6UDBkjCPHU1ogoVcVMKRjETwpBonFJcz/k2MRU=","CopyToOutputDirectory":"Never","CopyToPublishDirectory":"PreserveNewest","OriginalItemSpec":"wwwroot\\chunk-UJ7--WjT.js","FileLength":45866,"LastWriteTime":"2026-06-30T01:28:48.4844822+00:00"},"JCfmUn9DQGohrkt0dkNHgnj2lj468IilPQMEaw3aJNM=":{"Identity":"E:\\private\\structo\\structo\\Structo.API\\wwwroot\\chunk-LKO4NQtX.js","SourceId":"Structo.API","SourceType":"Discovered","ContentRoot":"E:\\private\\structo\\structo\\Structo.API\\wwwroot\\","BasePath":"_content/Structo.API","RelativePath":"chunk-LKO4NQtX#[.{fingerprint}]?.js","AssetKind":"All","AssetMode":"All","AssetRole":"Primary","AssetMergeBehavior":null,"AssetMergeSource":"","RelatedAsset":null,"AssetTraitName":null,"AssetTraitValue":null,"Fingerprint":"75bd9j5ld6","Integrity":"VSG6fU96ODDTCiEEhLQbCw4EjH8rZYSKJs\u002BMcY0afG0=","CopyToOutputDirectory":"Never","CopyToPublishDirectory":"PreserveNewest","OriginalItemSpec":"wwwroot\\chunk-LKO4NQtX.js","FileLength":48368,"LastWriteTime":"2026-06-30T01:28:48.4767901+00:00"},"TPoiUCcAXjsM1R7g6iSvD2b7QvShCn9f1uigYSzAQ8E=":{"Identity":"E:\\private\\structo\\structo\\Structo.API\\wwwroot\\chunk-hiR-rFYe.js","SourceId":"Structo.API","SourceType":"Discovered","ContentRoot":"E:\\private\\structo\\structo\\Structo.API\\wwwroot\\","BasePath":"_content/Structo.API","RelativePath":"chunk-hiR-rFYe#[.{fingerprint}]?.js","AssetKind":"All","AssetMode":"All","AssetRole":"Primary","AssetMergeBehavior":null,"AssetMergeSource":"","RelatedAsset":null,"AssetTraitName":null,"AssetTraitValue":null,"Fingerprint":"bp3g4kwym8","Integrity":"QbX8\u002B0PYr\u002B3Qa/lnTHhymgmNpbcoSlXx\u002BY02UsVLJHk=","CopyToOutputDirectory":"Never","CopyToPublishDirectory":"PreserveNewest","OriginalItemSpec":"wwwroot\\chunk-hiR-rFYe.js","FileLength":8755,"LastWriteTime":"2026-06-30T01:28:48.4844822+00:00"},"kmMqUrgMSskAHMMFQjZhvSTDrVI/n0QUrlnzrjhY/Ts=":{"Identity":"E:\\private\\structo\\structo\\Structo.API\\wwwroot\\chunk-fWaiy751.js","SourceId":"Structo.API","SourceType":"Discovered","ContentRoot":"E:\\private\\structo\\structo\\Structo.API\\wwwroot\\","BasePath":"_content/Structo.API","RelativePath":"chunk-fWaiy751#[.{fingerprint}]?.js","AssetKind":"All","AssetMode":"All","AssetRole":"Primary","AssetMergeBehavior":null,"AssetMergeSource":"","RelatedAsset":null,"AssetTraitName":null,"AssetTraitValue":null,"Fingerprint":"ywszpoqp1l","Integrity":"3onldsM5EpuNqgEQrkZzTgE0hXVBXivobPhl2h5Pmx0=","CopyToOutputDirectory":"Never","CopyToPublishDirectory":"PreserveNewest","OriginalItemSpec":"wwwroot\\chunk-fWaiy751.js","FileLength":53979,"LastWriteTime":"2026-06-30T01:28:48.4844822+00:00"},"d8dxIEQg7ZAF5LkmiKn7nH4QPTEYPO7Ac/eRcn2z6xU=":{"Identity":"E:\\private\\structo\\structo\\Structo.API\\wwwroot\\chunk-Dzqg54Lk.js","SourceId":"Structo.API","SourceType":"Discovered","ContentRoot":"E:\\private\\structo\\structo\\Structo.API\\wwwroot\\","BasePath":"_content/Structo.API","RelativePath":"chunk-Dzqg54Lk#[.{fingerprint}]?.js","AssetKind":"All","AssetMode":"All","AssetRole":"Primary","AssetMergeBehavior":null,"AssetMergeSource":"","RelatedAsset":null,"AssetTraitName":null,"AssetTraitValue":null,"Fingerprint":"4uzxcx3w76","Integrity":"VOxgKkrkxF21xtnQ33aYQ3m1RwbDZ2FN4TSH9gGksUA=","CopyToOutputDirectory":"Never","CopyToPublishDirectory":"PreserveNewest","OriginalItemSpec":"wwwroot\\chunk-Dzqg54Lk.js","FileLength":1822,"LastWriteTime":"2026-06-30T01:28:48.4844822+00:00"},"NKC/a3GCfq0HwhMOzEIyafLYCFVFg1US\u002BnhLTgkaZ0c=":{"Identity":"E:\\private\\structo\\structo\\Structo.API\\wwwroot\\chunk-DnziA9Jf.js","SourceId":"Structo.API","SourceType":"Discovered","ContentRoot":"E:\\private\\structo\\structo\\Structo.API\\wwwroot\\","BasePath":"_content/Structo.API","RelativePath":"chunk-DnziA9Jf#[.{fingerprint}]?.js","AssetKind":"All","AssetMode":"All","AssetRole":"Primary","AssetMergeBehavior":null,"AssetMergeSource":"","RelatedAsset":null,"AssetTraitName":null,"AssetTraitValue":null,"Fingerprint":"5bhd6qmt41","Integrity":"H1mnY5WxXvjKmdch134OzzkWinRXaI2ZKkgrFhJRsF0=","CopyToOutputDirectory":"Never","CopyToPublishDirectory":"PreserveNewest","OriginalItemSpec":"wwwroot\\chunk-DnziA9Jf.js","FileLength":79636,"LastWriteTime":"2026-06-30T01:28:48.4767901+00:00"},"8ks3nQ5u1UI2DF7D0fU1fHUJDUK9jJDeqq49vLtozPk=":{"Identity":"E:\\private\\structo\\structo\\Structo.API\\wwwroot\\chunk-CPQNKMOH.js","SourceId":"Structo.API","SourceType":"Discovered","ContentRoot":"E:\\private\\structo\\structo\\Structo.API\\wwwroot\\","BasePath":"_content/Structo.API","RelativePath":"chunk-CPQNKMOH#[.{fingerprint}]?.js","AssetKind":"All","AssetMode":"All","AssetRole":"Primary","AssetMergeBehavior":null,"AssetMergeSource":"","RelatedAsset":null,"AssetTraitName":null,"AssetTraitValue":null,"Fingerprint":"9zuvwfi7ip","Integrity":"a7VMGkkUJfC00OLLNp83My4\u002BCY0WzESMa45RblpU9Cs=","CopyToOutputDirectory":"Never","CopyToPublishDirectory":"PreserveNewest","OriginalItemSpec":"wwwroot\\chunk-CPQNKMOH.js","FileLength":21946,"LastWriteTime":"2026-06-30T01:28:48.4767901+00:00"},"ij\u002BC\u002BB77ZoU9LvrxrOtEaZn3wE1IhaRFBL4jWSYo3C0=":{"Identity":"E:\\private\\structo\\structo\\Structo.API\\wwwroot\\chunk-C4o2-4xJ.js","SourceId":"Structo.API","SourceType":"Discovered","ContentRoot":"E:\\private\\structo\\structo\\Structo.API\\wwwroot\\","BasePath":"_content/Structo.API","RelativePath":"chunk-C4o2-4xJ#[.{fingerprint}]?.js","AssetKind":"All","AssetMode":"All","AssetRole":"Primary","AssetMergeBehavior":null,"AssetMergeSource":"","RelatedAsset":null,"AssetTraitName":null,"AssetTraitValue":null,"Fingerprint":"xf2gwq1pbm","Integrity":"XYjqFqUSJBZvMjdCTlMnN/3kEWH2yT268iYXr7x9W/I=","CopyToOutputDirectory":"Never","CopyToPublishDirectory":"PreserveNewest","OriginalItemSpec":"wwwroot\\chunk-C4o2-4xJ.js","FileLength":18138,"LastWriteTime":"2026-06-30T01:28:48.4767901+00:00"},"/bm7SGeStM6JxqcQoCjse94MsKxznheYFjUDmlSoiII=":{"Identity":"E:\\private\\structo\\structo\\Structo.API\\wwwroot\\chunk-BrraIxHb.js","SourceId":"Structo.API","SourceType":"Discovered","ContentRoot":"E:\\private\\structo\\structo\\Structo.API\\wwwroot\\","BasePath":"_content/Structo.API","RelativePath":"chunk-BrraIxHb#[.{fingerprint}]?.js","AssetKind":"All","AssetMode":"All","AssetRole":"Primary","AssetMergeBehavior":null,"AssetMergeSource":"","RelatedAsset":null,"AssetTraitName":null,"AssetTraitValue":null,"Fingerprint":"8zjcm8mz0e","Integrity":"JAaohEWYJXBnTlsu5bzunzA66twvelb02S22hJXJxIE=","CopyToOutputDirectory":"Never","CopyToPublishDirectory":"PreserveNewest","OriginalItemSpec":"wwwroot\\chunk-BrraIxHb.js","FileLength":9681,"LastWriteTime":"2026-06-30T01:28:48.4767901+00:00"},"PHSmeVPpf2d5w\u002BGdMRwoi1H7moFsRfep1gjAwUgNnKY=":{"Identity":"E:\\private\\structo\\structo\\Structo.API\\wwwroot\\chunk-BiKyJk17.js","SourceId":"Structo.API","SourceType":"Discovered","ContentRoot":"E:\\private\\structo\\structo\\Structo.API\\wwwroot\\","BasePath":"_content/Structo.API","RelativePath":"chunk-BiKyJk17#[.{fingerprint}]?.js","AssetKind":"All","AssetMode":"All","AssetRole":"Primary","AssetMergeBehavior":null,"AssetMergeSource":"","RelatedAsset":null,"AssetTraitName":null,"AssetTraitValue":null,"Fingerprint":"hj0sgbihg9","Integrity":"Q5L3\u002BVn/I3S1/0ELMwP7aXMfXoX\u002BYH9viIOLS9F/sVE=","CopyToOutputDirectory":"Never","CopyToPublishDirectory":"PreserveNewest","OriginalItemSpec":"wwwroot\\chunk-BiKyJk17.js","FileLength":1992,"LastWriteTime":"2026-06-30T01:28:48.4844822+00:00"},"ZgEPg7Jt26YY0Fd/YPTJwhlKfWpR3LCud0PttwqfYqo=":{"Identity":"E:\\private\\structo\\structo\\Structo.API\\wwwroot\\chunk-BAoPwboW.js","SourceId":"Structo.API","SourceType":"Discovered","ContentRoot":"E:\\private\\structo\\structo\\Structo.API\\wwwroot\\","BasePath":"_content/Structo.API","RelativePath":"chunk-BAoPwboW#[.{fingerprint}]?.js","AssetKind":"All","AssetMode":"All","AssetRole":"Primary","AssetMergeBehavior":null,"AssetMergeSource":"","RelatedAsset":null,"AssetTraitName":null,"AssetTraitValue":null,"Fingerprint":"31n1u9iubd","Integrity":"12zLEqtnbKdrNNV\u002BjwbFvPXRWCNxgJ9Foxf\u002BclmdE5Y=","CopyToOutputDirectory":"Never","CopyToPublishDirectory":"PreserveNewest","OriginalItemSpec":"wwwroot\\chunk-BAoPwboW.js","FileLength":13406,"LastWriteTime":"2026-06-30T01:28:48.4767901+00:00"},"vTnqz\u002BxjeryvkeVkzmL9cgQtIjXyFaqPqDchX1uanGw=":{"Identity":"E:\\private\\structo\\structo\\Structo.API\\wwwroot\\chunk-B5oFTYuG.js","SourceId":"Structo.API","SourceType":"Discovered","ContentRoot":"E:\\private\\structo\\structo\\Structo.API\\wwwroot\\","BasePath":"_content/Structo.API","RelativePath":"chunk-B5oFTYuG#[.{fingerprint}]?.js","AssetKind":"All","AssetMode":"All","AssetRole":"Primary","AssetMergeBehavior":null,"AssetMergeSource":"","RelatedAsset":null,"AssetTraitName":null,"AssetTraitValue":null,"Fingerprint":"dk4o73mg8e","Integrity":"4x/8FvcQc6bN6hdpbijnYW/Jw4sfs0XQjgrcW3Dw5ZI=","CopyToOutputDirectory":"Never","CopyToPublishDirectory":"PreserveNewest","OriginalItemSpec":"wwwroot\\chunk-B5oFTYuG.js","FileLength":3875,"LastWriteTime":"2026-06-30T01:28:48.4767901+00:00"},"Nh9cyM7f4gTOUsXYky3iwx\u002BZgJRRAtKZNs0Xo6Quil8=":{"Identity":"E:\\private\\structo\\structo\\Structo.API\\wwwroot\\assets\\i18n\\en.json","SourceId":"Structo.API","SourceType":"Discovered","ContentRoot":"E:\\private\\structo\\structo\\Structo.API\\wwwroot\\","BasePath":"_content/Structo.API","RelativePath":"assets/i18n/en#[.{fingerprint}]?.json","AssetKind":"All","AssetMode":"All","AssetRole":"Primary","AssetMergeBehavior":null,"AssetMergeSource":"","RelatedAsset":null,"AssetTraitName":null,"AssetTraitValue":null,"Fingerprint":"wpn3sn0yam","Integrity":"LI3Ef7z43RSAVG9XMWmtUaeAvQFrMdAHxXXzbzD2haA=","CopyToOutputDirectory":"Never","CopyToPublishDirectory":"PreserveNewest","OriginalItemSpec":"wwwroot\\assets\\i18n\\en.json","FileLength":14134,"LastWriteTime":"2026-06-28T05:54:52.035+00:00"},"VcFc75hEssvuHgbAyyMAonWUwx4rJS7RGv9jNv76JGU=":{"Identity":"E:\\private\\structo\\structo\\Structo.API\\wwwroot\\assets\\i18n\\ar.json","SourceId":"Structo.API","SourceType":"Discovered","ContentRoot":"E:\\private\\structo\\structo\\Structo.API\\wwwroot\\","BasePath":"_content/Structo.API","RelativePath":"assets/i18n/ar#[.{fingerprint}]?.json","AssetKind":"All","AssetMode":"All","AssetRole":"Primary","AssetMergeBehavior":null,"AssetMergeSource":"","RelatedAsset":null,"AssetTraitName":null,"AssetTraitValue":null,"Fingerprint":"kknxagb79n","Integrity":"lO8wtQg1soos1DWiBaoBe22emVCOIaGVgrRtj2o4uRQ=","CopyToOutputDirectory":"Never","CopyToPublishDirectory":"PreserveNewest","OriginalItemSpec":"wwwroot\\assets\\i18n\\ar.json","FileLength":18975,"LastWriteTime":"2026-06-28T05:54:52.034+00:00"}},"CachedCopyCandidates":{}}