{"GlobalPropertiesHash":"HWfhOt3WlBV6RpSeDGzsxBusV2HuExvp77Qi2SrWaXA=","FingerprintPatternsHash":"gq3WsqcKBUGTSNle7RKKyXRIwh7M8ccEqOqYvIzoM04=","PropertyOverridesHash":"8ZRc1sGeVrPBx4lD717BgRaQekyh78QKV9SKsdt638U=","InputHashes":["55kJUlpBqhvcIZKd2Tpx4G0xdXPHtL6dsLyibGBLyaM=","UVyCOgk1L0TpZ0fVgbgK3MBWCbZ1Z7zNfJ3x\u002BjnZnnM=","Xolh9wiFG9aGxn\u002BnWEDAZ1Lyvar7CPskgts/8KYmQJo=","HAaT9oQEkH57G5mUNR1BqltjEebbpuetl\u002BoCafK5gAc=","0ofb6DNoMXgp07UHTcxR3G\u002Bkp3EJ9v3YaEqz3UvCb/Y=","nVrTkISkBns26ujpvwFK4zVoYcokbyTr4HDtIYwtuBo=","eqaVzxWSoTpQ3C1i8CAS/VCQwiWCAE/57ucXlTHMR1s=","FIMAONeR603MkrLl/ctDKaf/sbVFXaJI89uH80LJTuU=","F5gGa1Kyjm1/btN0a36Bob5f77Q9KBJEYwjuPUpBz\u002Bs=","VGfKy3kUBdPGuen2IL2n024Z/wA0fRJS25WcSKS5nzg=","biaHy5mpa8SFbzOpJxv\u002BVVRlBWv75CZUEvmOc1pC/rQ=","31vdweOl4R3OqM89lB8yV8xH3x/I\u002BXKhvAcucmFLIyA=","1lqle0bdou44polcjBhONXe8dd/ll\u002BooupBUvXcbD5g=","m\u002BizBgrG0F9QoF7BaEWxY9nqzPkOxZHE6sEpLLK/ed0=","gcZIXlu8Mwg6aNNpw2UoqU0bhKmsPmvlIn8PzUFDtgs=","IHRwwDKqbAR8O4Lf3ObVkFvh9UVuGfOgp8w4uOfxgB8=","2w9azAm4NaLP8NGRwCtRhuvJpqnIlmC3svvYiJssams=","ocBozQaIRvSnpYLXgL63xTxdnibtBZmmWae/jw2M59M=","nchy3X1Arf2cQZcP91a0pvdwWxoT7UMPczJRXTutqQY=","N3jod9wqOnhl/Wr8g\u002B3Dtb2JK9vTgpWAmoUWudsbTMc=","BXt3y80BFlCEF00RhXRKMxY2zfaTji4RZuoo6Gb\u002B6UI=","UhwYEn2Xs79C8luKQO8cp5msBS0e64fNp25lam4lCi8="],"CachedAssets":{"55kJUlpBqhvcIZKd2Tpx4G0xdXPHtL6dsLyibGBLyaM=":{"Identity":"E:\\private\\structo\\structo\\Structo.API\\wwwroot\\3rdpartylicenses.txt","SourceId":"Structo.API","SourceType":"Discovered","ContentRoot":"E:\\private\\structo\\structo\\Structo.API\\wwwroot\\","BasePath":"/","RelativePath":"3rdpartylicenses#[.{fingerprint}]?.txt","AssetKind":"All","AssetMode":"All","AssetRole":"Primary","AssetMergeBehavior":null,"AssetMergeSource":"","RelatedAsset":null,"AssetTraitName":null,"AssetTraitValue":null,"Fingerprint":"iunqrjy43x","Integrity":"OkIxDQ1ZvE55lB7wSI6lvfZ5BvBpUjHdlrj0V/ACHiM=","CopyToOutputDirectory":"Never","CopyToPublishDirectory":"PreserveNewest","OriginalItemSpec":"wwwroot\\3rdpartylicenses.txt","FileLength":20782,"LastWriteTime":"2026-06-29T21:24:27.8159908+00:00"},"UVyCOgk1L0TpZ0fVgbgK3MBWCbZ1Z7zNfJ3x\u002BjnZnnM=":{"Identity":"E:\\private\\structo\\structo\\Structo.API\\wwwroot\\assets\\i18n\\ar.json","SourceId":"Structo.API","SourceType":"Discovered","ContentRoot":"E:\\private\\structo\\structo\\Structo.API\\wwwroot\\","BasePath":"/","RelativePath":"assets/i18n/ar#[.{fingerprint}]?.json","AssetKind":"All","AssetMode":"All","AssetRole":"Primary","AssetMergeBehavior":null,"AssetMergeSource":"","RelatedAsset":null,"AssetTraitName":null,"AssetTraitValue":null,"Fingerprint":"kknxagb79n","Integrity":"lO8wtQg1soos1DWiBaoBe22emVCOIaGVgrRtj2o4uRQ=","CopyToOutputDirectory":"Never","CopyToPublishDirectory":"PreserveNewest","OriginalItemSpec":"wwwroot\\assets\\i18n\\ar.json","FileLength":18975,"LastWriteTime":"2026-06-28T05:54:52.034+00:00"},"Xolh9wiFG9aGxn\u002BnWEDAZ1Lyvar7CPskgts/8KYmQJo=":{"Identity":"E:\\private\\structo\\structo\\Structo.API\\wwwroot\\assets\\i18n\\en.json","SourceId":"Structo.API","SourceType":"Discovered","ContentRoot":"E:\\private\\structo\\structo\\Structo.API\\wwwroot\\","BasePath":"/","RelativePath":"assets/i18n/en#[.{fingerprint}]?.json","AssetKind":"All","AssetMode":"All","AssetRole":"Primary","AssetMergeBehavior":null,"AssetMergeSource":"","RelatedAsset":null,"AssetTraitName":null,"AssetTraitValue":null,"Fingerprint":"wpn3sn0yam","Integrity":"LI3Ef7z43RSAVG9XMWmtUaeAvQFrMdAHxXXzbzD2haA=","CopyToOutputDirectory":"Never","CopyToPublishDirectory":"PreserveNewest","OriginalItemSpec":"wwwroot\\assets\\i18n\\en.json","FileLength":14134,"LastWriteTime":"2026-06-28T05:54:52.035+00:00"},"HAaT9oQEkH57G5mUNR1BqltjEebbpuetl\u002BoCafK5gAc=":{"Identity":"E:\\private\\structo\\structo\\Structo.API\\wwwroot\\chunk-BuwjUZsd.js","SourceId":"Structo.API","SourceType":"Discovered","ContentRoot":"E:\\private\\structo\\structo\\Structo.API\\wwwroot\\","BasePath":"/","RelativePath":"chunk-BuwjUZsd#[.{fingerprint}]?.js","AssetKind":"All","AssetMode":"All","AssetRole":"Primary","AssetMergeBehavior":null,"AssetMergeSource":"","RelatedAsset":null,"AssetTraitName":null,"AssetTraitValue":null,"Fingerprint":"pjw6vw1ss0","Integrity":"Rfk9npoebJ0O5SqrtUd8x5DBwrOiIsBz7KVcwcRduBo=","CopyToOutputDirectory":"Never","CopyToPublishDirectory":"PreserveNewest","OriginalItemSpec":"wwwroot\\chunk-BuwjUZsd.js","FileLength":13271,"LastWriteTime":"2026-06-29T21:24:27.8159908+00:00"},"0ofb6DNoMXgp07UHTcxR3G\u002Bkp3EJ9v3YaEqz3UvCb/Y=":{"Identity":"E:\\private\\structo\\structo\\Structo.API\\wwwroot\\chunk-BvGEeTWA.js","SourceId":"Structo.API","SourceType":"Discovered","ContentRoot":"E:\\private\\structo\\structo\\Structo.API\\wwwroot\\","BasePath":"/","RelativePath":"chunk-BvGEeTWA#[.{fingerprint}]?.js","AssetKind":"All","AssetMode":"All","AssetRole":"Primary","AssetMergeBehavior":null,"AssetMergeSource":"","RelatedAsset":null,"AssetTraitName":null,"AssetTraitValue":null,"Fingerprint":"9bcdy5w80m","Integrity":"lRViT0Pm5pwdYyv6VvSItbjEXsS\u002BvuSOokNYhbccDxo=","CopyToOutputDirectory":"Never","CopyToPublishDirectory":"PreserveNewest","OriginalItemSpec":"wwwroot\\chunk-BvGEeTWA.js","FileLength":9679,"LastWriteTime":"2026-06-29T21:24:27.8159908+00:00"},"nVrTkISkBns26ujpvwFK4zVoYcokbyTr4HDtIYwtuBo=":{"Identity":"E:\\private\\structo\\structo\\Structo.API\\wwwroot\\chunk-ByCE4MGr.js","SourceId":"Structo.API","SourceType":"Discovered","ContentRoot":"E:\\private\\structo\\structo\\Structo.API\\wwwroot\\","BasePath":"/","RelativePath":"chunk-ByCE4MGr#[.{fingerprint}]?.js","AssetKind":"All","AssetMode":"All","AssetRole":"Primary","AssetMergeBehavior":null,"AssetMergeSource":"","RelatedAsset":null,"AssetTraitName":null,"AssetTraitValue":null,"Fingerprint":"smv60dwisg","Integrity":"XEaC8ioNNY/NSk0yjmKOkWrJoS7kk8IBMCi/UeGc/ns=","CopyToOutputDirectory":"Never","CopyToPublishDirectory":"PreserveNewest","OriginalItemSpec":"wwwroot\\chunk-ByCE4MGr.js","FileLength":79634,"LastWriteTime":"2026-06-29T21:24:27.8159908+00:00"},"eqaVzxWSoTpQ3C1i8CAS/VCQwiWCAE/57ucXlTHMR1s=":{"Identity":"E:\\private\\structo\\structo\\Structo.API\\wwwroot\\chunk-CEZtH9tC.js","SourceId":"Structo.API","SourceType":"Discovered","ContentRoot":"E:\\private\\structo\\structo\\Structo.API\\wwwroot\\","BasePath":"/","RelativePath":"chunk-CEZtH9tC#[.{fingerprint}]?.js","AssetKind":"All","AssetMode":"All","AssetRole":"Primary","AssetMergeBehavior":null,"AssetMergeSource":"","RelatedAsset":null,"AssetTraitName":null,"AssetTraitValue":null,"Fingerprint":"fhapdvtv13","Integrity":"U5pEu8vAIQYQuY84IjArp1O20DNqS/0nUBkykCyFSEE=","CopyToOutputDirectory":"Never","CopyToPublishDirectory":"PreserveNewest","OriginalItemSpec":"wwwroot\\chunk-CEZtH9tC.js","FileLength":75768,"LastWriteTime":"2026-06-29T21:24:27.8159908+00:00"},"FIMAONeR603MkrLl/ctDKaf/sbVFXaJI89uH80LJTuU=":{"Identity":"E:\\private\\structo\\structo\\Structo.API\\wwwroot\\chunk-CUR1jdwX.js","SourceId":"Structo.API","SourceType":"Discovered","ContentRoot":"E:\\private\\structo\\structo\\Structo.API\\wwwroot\\","BasePath":"/","RelativePath":"chunk-CUR1jdwX#[.{fingerprint}]?.js","AssetKind":"All","AssetMode":"All","AssetRole":"Primary","AssetMergeBehavior":null,"AssetMergeSource":"","RelatedAsset":null,"AssetTraitName":null,"AssetTraitValue":null,"Fingerprint":"sofgjwy3w6","Integrity":"lPmlqDFGHbzLZ/1\u002BggSI9D6c86t6jhbZDfnMbzL/E0c=","CopyToOutputDirectory":"Never","CopyToPublishDirectory":"PreserveNewest","OriginalItemSpec":"wwwroot\\chunk-CUR1jdwX.js","FileLength":8757,"LastWriteTime":"2026-06-29T21:24:27.8159908+00:00"},"F5gGa1Kyjm1/btN0a36Bob5f77Q9KBJEYwjuPUpBz\u002Bs=":{"Identity":"E:\\private\\structo\\structo\\Structo.API\\wwwroot\\chunk-CuvxcTBv.js","SourceId":"Structo.API","SourceType":"Discovered","ContentRoot":"E:\\private\\structo\\structo\\Structo.API\\wwwroot\\","BasePath":"/","RelativePath":"chunk-CuvxcTBv#[.{fingerprint}]?.js","AssetKind":"All","AssetMode":"All","AssetRole":"Primary","AssetMergeBehavior":null,"AssetMergeSource":"","RelatedAsset":null,"AssetTraitName":null,"AssetTraitValue":null,"Fingerprint":"xglu9u4rp1","Integrity":"z1bqljxHDy29TI1g6TiSiWhicTlE3LzwtwY9AZj/bV0=","CopyToOutputDirectory":"Never","CopyToPublishDirectory":"PreserveNewest","OriginalItemSpec":"wwwroot\\chunk-CuvxcTBv.js","FileLength":49028,"LastWriteTime":"2026-06-29T21:24:27.8159908+00:00"},"VGfKy3kUBdPGuen2IL2n024Z/wA0fRJS25WcSKS5nzg=":{"Identity":"E:\\private\\structo\\structo\\Structo.API\\wwwroot\\chunk-CZqU89Ji.js","SourceId":"Structo.API","SourceType":"Discovered","ContentRoot":"E:\\private\\structo\\structo\\Structo.API\\wwwroot\\","BasePath":"/","RelativePath":"chunk-CZqU89Ji#[.{fingerprint}]?.js","AssetKind":"All","AssetMode":"All","AssetRole":"Primary","AssetMergeBehavior":null,"AssetMergeSource":"","RelatedAsset":null,"AssetTraitName":null,"AssetTraitValue":null,"Fingerprint":"w08qq7ggfg","Integrity":"4H6E3f198m7zkr9EU4eTVl8V/gKVeRH5bMTFjeR4Exs=","CopyToOutputDirectory":"Never","CopyToPublishDirectory":"PreserveNewest","OriginalItemSpec":"wwwroot\\chunk-CZqU89Ji.js","FileLength":3876,"LastWriteTime":"2026-06-29T21:24:27.8159908+00:00"},"biaHy5mpa8SFbzOpJxv\u002BVVRlBWv75CZUEvmOc1pC/rQ=":{"Identity":"E:\\private\\structo\\structo\\Structo.API\\wwwroot\\chunk-DeY6SRAG.js","SourceId":"Structo.API","SourceType":"Discovered","ContentRoot":"E:\\private\\structo\\structo\\Structo.API\\wwwroot\\","BasePath":"/","RelativePath":"chunk-DeY6SRAG#[.{fingerprint}]?.js","AssetKind":"All","AssetMode":"All","AssetRole":"Primary","AssetMergeBehavior":null,"AssetMergeSource":"","RelatedAsset":null,"AssetTraitName":null,"AssetTraitValue":null,"Fingerprint":"teo76ap86i","Integrity":"q8rdzmRTOj7SYZOtTJda2TdTOkOebo4FBWbHVwk04lU=","CopyToOutputDirectory":"Never","CopyToPublishDirectory":"PreserveNewest","OriginalItemSpec":"wwwroot\\chunk-DeY6SRAG.js","FileLength":1428,"LastWriteTime":"2026-06-29T21:24:27.8159908+00:00"},"31vdweOl4R3OqM89lB8yV8xH3x/I\u002BXKhvAcucmFLIyA=":{"Identity":"E:\\private\\structo\\structo\\Structo.API\\wwwroot\\chunk-Dl4ykNVl.js","SourceId":"Structo.API","SourceType":"Discovered","ContentRoot":"E:\\private\\structo\\structo\\Structo.API\\wwwroot\\","BasePath":"/","RelativePath":"chunk-Dl4ykNVl#[.{fingerprint}]?.js","AssetKind":"All","AssetMode":"All","AssetRole":"Primary","AssetMergeBehavior":null,"AssetMergeSource":"","RelatedAsset":null,"AssetTraitName":null,"AssetTraitValue":null,"Fingerprint":"z09wwl6vwq","Integrity":"s6k2VNlocPh3SqWjMkiW4mx8weSVpvzn6295TBeRW44=","CopyToOutputDirectory":"Never","CopyToPublishDirectory":"PreserveNewest","OriginalItemSpec":"wwwroot\\chunk-Dl4ykNVl.js","FileLength":1817,"LastWriteTime":"2026-06-29T21:24:27.8159908+00:00"},"1lqle0bdou44polcjBhONXe8dd/ll\u002BooupBUvXcbD5g=":{"Identity":"E:\\private\\structo\\structo\\Structo.API\\wwwroot\\chunk-DW5z40jm.js","SourceId":"Structo.API","SourceType":"Discovered","ContentRoot":"E:\\private\\structo\\structo\\Structo.API\\wwwroot\\","BasePath":"/","RelativePath":"chunk-DW5z40jm#[.{fingerprint}]?.js","AssetKind":"All","AssetMode":"All","AssetRole":"Primary","AssetMergeBehavior":null,"AssetMergeSource":"","RelatedAsset":null,"AssetTraitName":null,"AssetTraitValue":null,"Fingerprint":"j14sm5m7ab","Integrity":"idLd3TqROOrg46qWNlOFo0b2bGMQnohpEMmi4JjwVM4=","CopyToOutputDirectory":"Never","CopyToPublishDirectory":"PreserveNewest","OriginalItemSpec":"wwwroot\\chunk-DW5z40jm.js","FileLength":53977,"LastWriteTime":"2026-06-29T21:24:27.8159908+00:00"},"m\u002BizBgrG0F9QoF7BaEWxY9nqzPkOxZHE6sEpLLK/ed0=":{"Identity":"E:\\private\\structo\\structo\\Structo.API\\wwwroot\\chunk-DZQD5Co7.js","SourceId":"Structo.API","SourceType":"Discovered","ContentRoot":"E:\\private\\structo\\structo\\Structo.API\\wwwroot\\","BasePath":"/","RelativePath":"chunk-DZQD5Co7#[.{fingerprint}]?.js","AssetKind":"All","AssetMode":"All","AssetRole":"Primary","AssetMergeBehavior":null,"AssetMergeSource":"","RelatedAsset":null,"AssetTraitName":null,"AssetTraitValue":null,"Fingerprint":"z9c5qhqj8p","Integrity":"Z2s1MOCkCKN6\u002BlRGfO6ZxAuHyN9gTZDOY0ndPSkhMnM=","CopyToOutputDirectory":"Never","CopyToPublishDirectory":"PreserveNewest","OriginalItemSpec":"wwwroot\\chunk-DZQD5Co7.js","FileLength":20436,"LastWriteTime":"2026-06-29T21:24:27.8159908+00:00"},"gcZIXlu8Mwg6aNNpw2UoqU0bhKmsPmvlIn8PzUFDtgs=":{"Identity":"E:\\private\\structo\\structo\\Structo.API\\wwwroot\\chunk-_OkUl2tP.js","SourceId":"Structo.API","SourceType":"Discovered","ContentRoot":"E:\\private\\structo\\structo\\Structo.API\\wwwroot\\","BasePath":"/","RelativePath":"chunk-_OkUl2tP#[.{fingerprint}]?.js","AssetKind":"All","AssetMode":"All","AssetRole":"Primary","AssetMergeBehavior":null,"AssetMergeSource":"","RelatedAsset":null,"AssetTraitName":null,"AssetTraitValue":null,"Fingerprint":"hfagu7izyz","Integrity":"My35ltZdN2/kEsPiYbGkmv9RgnA7I/RcdUUve2Cb0rU=","CopyToOutputDirectory":"Never","CopyToPublishDirectory":"PreserveNewest","OriginalItemSpec":"wwwroot\\chunk-_OkUl2tP.js","FileLength":45859,"LastWriteTime":"2026-06-29T21:24:27.8159908+00:00"},"IHRwwDKqbAR8O4Lf3ObVkFvh9UVuGfOgp8w4uOfxgB8=":{"Identity":"E:\\private\\structo\\structo\\Structo.API\\wwwroot\\favicon.ico","SourceId":"Structo.API","SourceType":"Discovered","ContentRoot":"E:\\private\\structo\\structo\\Structo.API\\wwwroot\\","BasePath":"/","RelativePath":"favicon#[.{fingerprint}]?.ico","AssetKind":"All","AssetMode":"All","AssetRole":"Primary","AssetMergeBehavior":null,"AssetMergeSource":"","RelatedAsset":null,"AssetTraitName":null,"AssetTraitValue":null,"Fingerprint":"vagikyz9qx","Integrity":"\u002BRAr6AKXwFKSB2B75Sd7T5C8qJ1lmI\u002BhdxuRx4lOgV8=","CopyToOutputDirectory":"Never","CopyToPublishDirectory":"PreserveNewest","OriginalItemSpec":"wwwroot\\favicon.ico","FileLength":15086,"LastWriteTime":"2026-06-23T09:03:05.164+00:00"},"2w9azAm4NaLP8NGRwCtRhuvJpqnIlmC3svvYiJssams=":{"Identity":"E:\\private\\structo\\structo\\Structo.API\\wwwroot\\index.html","SourceId":"Structo.API","SourceType":"Discovered","ContentRoot":"E:\\private\\structo\\structo\\Structo.API\\wwwroot\\","BasePath":"/","RelativePath":"index#[.{fingerprint}]?.html","AssetKind":"All","AssetMode":"All","AssetRole":"Primary","AssetMergeBehavior":null,"AssetMergeSource":"","RelatedAsset":null,"AssetTraitName":null,"AssetTraitValue":null,"Fingerprint":"5abkm5ogr6","Integrity":"4//XWD7Oo3\u002BxkVSflMnQWCMhnwms5b/s/0g4nI610oc=","CopyToOutputDirectory":"Never","CopyToPublishDirectory":"PreserveNewest","OriginalItemSpec":"wwwroot\\index.html","FileLength":23566,"LastWriteTime":"2026-06-29T21:24:27.8159908+00:00"},"ocBozQaIRvSnpYLXgL63xTxdnibtBZmmWae/jw2M59M=":{"Identity":"E:\\private\\structo\\structo\\Structo.API\\wwwroot\\main-ZFZZHFNK.js","SourceId":"Structo.API","SourceType":"Discovered","ContentRoot":"E:\\private\\structo\\structo\\Structo.API\\wwwroot\\","BasePath":"/","RelativePath":"main-ZFZZHFNK#[.{fingerprint}]?.js","AssetKind":"All","AssetMode":"All","AssetRole":"Primary","AssetMergeBehavior":null,"AssetMergeSource":"","RelatedAsset":null,"AssetTraitName":null,"AssetTraitValue":null,"Fingerprint":"80r5m1ndsw","Integrity":"\u002BEGCH36NSogmVZhHK\u002Bgfi4GIDbMVYa5R0ak1stNSYv4=","CopyToOutputDirectory":"Never","CopyToPublishDirectory":"PreserveNewest","OriginalItemSpec":"wwwroot\\main-ZFZZHFNK.js","FileLength":330821,"LastWriteTime":"2026-06-29T21:24:27.8159908+00:00"},"nchy3X1Arf2cQZcP91a0pvdwWxoT7UMPczJRXTutqQY=":{"Identity":"E:\\private\\structo\\structo\\Structo.API\\wwwroot\\OneSignalSDKWorker.js","SourceId":"Structo.API","SourceType":"Discovered","ContentRoot":"E:\\private\\structo\\structo\\Structo.API\\wwwroot\\","BasePath":"/","RelativePath":"OneSignalSDKWorker#[.{fingerprint}]?.js","AssetKind":"All","AssetMode":"All","AssetRole":"Primary","AssetMergeBehavior":null,"AssetMergeSource":"","RelatedAsset":null,"AssetTraitName":null,"AssetTraitValue":null,"Fingerprint":"fp1x7dnec5","Integrity":"Hc44Lw6x1Jy40gNuUWvOJtdHfgwFO71Ud/H27IsWOEc=","CopyToOutputDirectory":"Never","CopyToPublishDirectory":"PreserveNewest","OriginalItemSpec":"wwwroot\\OneSignalSDKWorker.js","FileLength":75,"LastWriteTime":"2023-04-14T22:59:41+00:00"},"N3jod9wqOnhl/Wr8g\u002B3Dtb2JK9vTgpWAmoUWudsbTMc=":{"Identity":"E:\\private\\structo\\structo\\Structo.API\\wwwroot\\styles-HMQIAAGN.css","SourceId":"Structo.API","SourceType":"Discovered","ContentRoot":"E:\\private\\structo\\structo\\Structo.API\\wwwroot\\","BasePath":"/","RelativePath":"styles-HMQIAAGN#[.{fingerprint}]?.css","AssetKind":"All","AssetMode":"All","AssetRole":"Primary","AssetMergeBehavior":null,"AssetMergeSource":"","RelatedAsset":null,"AssetTraitName":null,"AssetTraitValue":null,"Fingerprint":"9pb1xwe72b","Integrity":"gy1Id9Zt9YD2J\u002BKn9B9IDb4ZQAMJJae3bLlwmAjYqRA=","CopyToOutputDirectory":"Never","CopyToPublishDirectory":"PreserveNewest","OriginalItemSpec":"wwwroot\\styles-HMQIAAGN.css","FileLength":96042,"LastWriteTime":"2026-06-29T21:24:27.8159908+00:00"}},"CachedCopyCandidates":{}}